sciagents/__init__.py
sciagents/llm.py
sciagents-0.0.3.dist-info/licenses/LICENSE
sciagents-0.0.3.dist-info/METADATA
sciagents-0.0.3.dist-info/WHEEL
sciagents-0.0.3.dist-info/top_level.txt
sciagents-0.0.3.dist-info/RECORD
