Metadata-Version: 2.4
Name: sciagents
Version: 0.0.3
Summary: Agents
Author-email: OPENAGS <pengsong.zhang@mail.utoronto.ca>
License: MIT License
Project-URL: Homepage, https://github.com/openags/SciAgents
Requires-Python: >=3.8
License-File: LICENSE
Requires-Dist: pydantic>=2.0
Requires-Dist: litellm
Requires-Dist: pyyaml
Requires-Dist: requests
Requires-Dist: numpy
Dynamic: license-file
